gsslt/__init__.py
gsslt/visualization.py
gsslt-0.1.1.dist-info/METADATA
gsslt-0.1.1.dist-info/WHEEL
gsslt-0.1.1.dist-info/entry_points.txt
gsslt-0.1.1.dist-info/licenses/LICENSE
gsslt-0.1.1.dist-info/RECORD
